include/PySysLinkBase/BlockEventsHandler.h
include/PySysLinkBase/BlockTypeSupportPluginLoader.h
include/PySysLinkBase/ConfigurationValue.h
include/PySysLinkBase/FullySupportedSignalValue.h
include/PySysLinkBase/IBlockEventsHandler.h
include/PySysLinkBase/IBlockFactory.h
include/PySysLinkBase/ISimulationBlock.h
include/PySysLinkBase/ModelParser.h
include/PySysLinkBase/PortLink.h
include/PySysLinkBase/SampleTime.h
include/PySysLinkBase/SimulationManager.h
include/PySysLinkBase/SimulationModel.h
include/PySysLinkBase/SimulationOptions.h
include/PySysLinkBase/SimulationOutput.h
include/PySysLinkBase/SpdlogManager.h
include/PySysLinkBase/BlockEvents/BlockEvent.h
include/PySysLinkBase/BlockEvents/ValueUpdateBlockEvent.h
include/PySysLinkBase/ContinuousAndOde/BasicOdeSolver.h
include/PySysLinkBase/ContinuousAndOde/EulerBackwardStepSolver.h
include/PySysLinkBase/ContinuousAndOde/EulerForwardStepSolver.h
include/PySysLinkBase/ContinuousAndOde/IOdeStepSolver.h
include/PySysLinkBase/ContinuousAndOde/ISimulationBlockWithContinuousStates.h
include/PySysLinkBase/ContinuousAndOde/OdeintImplicitStepSolver.h
include/PySysLinkBase/ContinuousAndOde/OdeintStepSolver.h
include/PySysLinkBase/ContinuousAndOde/SolverFactory.h
include/PySysLinkBase/PortsAndSignalValues/InputPort.h
include/PySysLinkBase/PortsAndSignalValues/OutputPort.h
include/PySysLinkBase/PortsAndSignalValues/Port.h
include/PySysLinkBase/PortsAndSignalValues/SignalValue.h
include/PySysLinkBase/PortsAndSignalValues/UnknownTypeSignalValue.h
include/eigen3/signature_of_eigen3_matrix_library
include/eigen3/Eigen/AccelerateSupport
include/eigen3/Eigen/Cholesky
include/eigen3/Eigen/CholmodSupport
include/eigen3/Eigen/Core
include/eigen3/Eigen/Dense
include/eigen3/Eigen/Eigen
include/eigen3/Eigen/Eigenvalues
include/eigen3/Eigen/Geometry
include/eigen3/Eigen/Householder
include/eigen3/Eigen/IterativeLinearSolvers
include/eigen3/Eigen/Jacobi
include/eigen3/Eigen/KLUSupport
pysyslink_base-0.1.0.dist-info/METADATA
pysyslink_base-0.1.0.dist-info/WHEEL
pysyslink_base-0.1.0.dist-info/RECORD
pysyslink_base-0.1.0.dist-info/licenses/LICENSE
