Metadata-Version: 2.2
Name: pysyslink_base
Version: 0.1.0
Summary: pysyslink-base, example of bindings with litgen
Author-Email: My Name <me@email.com>
Classifier: Development Status :: 4 - Beta
Classifier: License :: OSI Approved :: MIT License
Classifier: Programming Language :: Python :: 3 :: Only
Classifier: Programming Language :: Python :: 3.7
Classifier: Programming Language :: Python :: 3.8
Classifier: Programming Language :: Python :: 3.9
Classifier: Programming Language :: Python :: 3.10
Classifier: Programming Language :: Python :: 3.11
Classifier: Programming Language :: Python :: 3.12
Requires-Python: >=3.7
Requires-Dist: numpy
Requires-Dist: nanobind
Provides-Extra: test
Requires-Dist: pytest; extra == "test"
